bridgekeeper/__init__.py
bridgekeeper/apps.py
bridgekeeper/backend_tests.py
bridgekeeper/backends.py
bridgekeeper/conftest.py
bridgekeeper/mixins.py
bridgekeeper/permission_map.py
bridgekeeper/querysets.py
bridgekeeper/rest_framework.py
bridgekeeper/rest_framework_tests.py
bridgekeeper/rule_attribute_tests.py
bridgekeeper/rule_in_tests.py
bridgekeeper/rule_is_tests.py
bridgekeeper/rule_many_relation_tests.py
bridgekeeper/rule_r_tests.py
bridgekeeper/rule_relation_tests.py
bridgekeeper/rules.py
bridgekeeper-0.9.dist-info/LICENSE
bridgekeeper-0.9.dist-info/WHEEL
bridgekeeper-0.9.dist-info/METADATA
bridgekeeper-0.9.dist-info/RECORD
