Metadata-Version: 2.1
Name: bridgekeeper
Version: 0.9
Summary: Django permissions that work with QuerySets.
Home-page: https://bridgekeeper.leigh.party/
License: MIT
Author: Leigh Brenecki
Author-email: leigh@brenecki.id.au
Requires-Python: >=3.5
Classifier: License :: OSI Approved :: MIT License
Classifier: Programming Language :: Python :: 3
Classifier: Programming Language :: Python :: 3.5
Classifier: Programming Language :: Python :: 3.6
Classifier: Programming Language :: Python :: 3.7
Classifier: Programming Language :: Python :: 3.8
Project-URL: Repository, https://github.com/excitedleigh/bridgekeeper
